llama_index/llms/apertis/__init__.py
llama_index/llms/apertis/base.py
llama_index/llms/apertis/py.typed
llama_index_llms_apertis-0.1.0.dist-info/METADATA
llama_index_llms_apertis-0.1.0.dist-info/WHEEL
llama_index_llms_apertis-0.1.0.dist-info/licenses/LICENSE
llama_index_llms_apertis-0.1.0.dist-info/RECORD
